MANIFEST.in
README.md
setup.py
boilerplate/cli.py
delphai_boil.egg-info/PKG-INFO
delphai_boil.egg-info/SOURCES.txt
delphai_boil.egg-info/dependency_links.txt
delphai_boil.egg-info/entry_points.txt
delphai_boil.egg-info/requires.txt
delphai_boil.egg-info/top_level.txt