Metadata-Version: 2.1
Name: delphai-boil
Version: 1.0.1
Summary: A Python package to boilerblate Delphai minimal pakages.
Home-page: https://github.com/delphai/delphai-boilerplate
Author: Ahmed Mahmoud
Author-email: ahmed.mahmoud@delphai.com
License: MIT
Platform: UNKNOWN
Classifier: License :: OSI Approved :: MIT License
Classifier: Programming Language :: Python :: 3
Classifier: Programming Language :: Python :: 3.7
